README.md
setup.py
NHentaidesu/__init__.py
NHentaidesu/client.py
NHentaidesu/errors.py
NHentaidesu/scaffold.py
NHentaidesu/sync.py
NHentaidesu/utils.py
NHentaidesu.egg-info/PKG-INFO
NHentaidesu.egg-info/SOURCES.txt
NHentaidesu.egg-info/dependency_links.txt
NHentaidesu.egg-info/not-zip-safe
NHentaidesu.egg-info/requires.txt
NHentaidesu.egg-info/top_level.txt
NHentaidesu/methods/__init__.py
NHentaidesu/methods/doujinshi/__init__.py
NHentaidesu/methods/doujinshi/comments.py
NHentaidesu/methods/doujinshi/info.py
NHentaidesu/methods/doujinshi/related.py
NHentaidesu/methods/general/__init__.py
NHentaidesu/methods/general/new.py
NHentaidesu/methods/general/search.py
NHentaidesu/methods/general/tags.py
NHentaidesu/methods/general/user.py
NHentaidesu/types/__init__.py
NHentaidesu/types/list.py
NHentaidesu/types/object.py
NHentaidesu/types/doujinshi/__init__.py
NHentaidesu/types/doujinshi/comments.py
NHentaidesu/types/doujinshi/image.py
NHentaidesu/types/doujinshi/info.py
NHentaidesu/types/doujinshi/tags.py
NHentaidesu/types/general/__init__.py
NHentaidesu/types/general/user.py