Metadata-Version: 2.1
Name: NHentaidesu
Version: 1.6
Summary: NHentai API wrapper with hybrid runtime.
Home-page: https://github.com/rushkii/NHentaidesu
Author: Kiizuha
Author-email: riskimuhammmad1@gmail.com
License: MIT
Keywords: nhentai nhentaidesu nhentai-python nhentai python nhentai api
Platform: UNKNOWN
Classifier: Programming Language :: Python :: 3
Classifier: License :: OSI Approved :: MIT License
Classifier: Operating System :: OS Independent
